mkv_episode_matcher/.gitattributes
mkv_episode_matcher/__init__.py
mkv_episode_matcher/__main__.py
mkv_episode_matcher/asr_models.py
mkv_episode_matcher/cli.py
mkv_episode_matcher/episode_identification.py
mkv_episode_matcher/subtitle_utils.py
mkv_episode_matcher/tmdb_client.py
mkv_episode_matcher/utils.py
mkv_episode_matcher/backend/dependencies.py
mkv_episode_matcher/backend/main.py
mkv_episode_matcher/backend/socket_manager.py
mkv_episode_matcher/backend/routers/__init__.py
mkv_episode_matcher/backend/routers/match.py
mkv_episode_matcher/backend/routers/scan.py
mkv_episode_matcher/backend/routers/system.py
mkv_episode_matcher/backend/routers/websocket.py
mkv_episode_matcher/core/config_manager.py
mkv_episode_matcher/core/engine.py
mkv_episode_matcher/core/matcher.py
mkv_episode_matcher/core/model_registry.py
mkv_episode_matcher/core/models.py
mkv_episode_matcher/core/utils.py
mkv_episode_matcher/core/providers/asr.py
mkv_episode_matcher/core/providers/subtitles.py
mkv_episode_matcher/frontend/.gitignore
mkv_episode_matcher/frontend/README.md
mkv_episode_matcher/frontend/eslint.config.js
mkv_episode_matcher/frontend/index.html
mkv_episode_matcher/frontend/package-lock.json
mkv_episode_matcher/frontend/package.json
mkv_episode_matcher/frontend/tsconfig.app.json
mkv_episode_matcher/frontend/tsconfig.json
mkv_episode_matcher/frontend/tsconfig.node.json
mkv_episode_matcher/frontend/vite.config.ts
mkv_episode_matcher/frontend/public/vite.svg
mkv_episode_matcher/frontend/src/App.css
mkv_episode_matcher/frontend/src/App.tsx
mkv_episode_matcher/frontend/src/index.css
mkv_episode_matcher/frontend/src/main.tsx
mkv_episode_matcher/frontend/src/assets/react.svg
mkv_episode_matcher/frontend/src/components/FileBrowser.tsx
mkv_episode_matcher/frontend/src/components/FileReviewGrid.tsx
mkv_episode_matcher/frontend/src/components/Layout.tsx
mkv_episode_matcher/frontend/src/components/SettingsView.tsx
mkv_episode_matcher/frontend/src/components/Sidebar.tsx
mkv_episode_matcher-1.1.1.dist-info/licenses/LICENSE
mkv_episode_matcher-1.1.1.dist-info/METADATA
mkv_episode_matcher-1.1.1.dist-info/WHEEL
mkv_episode_matcher-1.1.1.dist-info/entry_points.txt
mkv_episode_matcher-1.1.1.dist-info/top_level.txt
mkv_episode_matcher-1.1.1.dist-info/RECORD
