Metadata-Version: 2.4
Name: mkv-episode-matcher
Version: 1.1.1
Summary: The MKV Episode Matcher is a tool for identifying TV series episodes from MKV files and renaming the files accordingly.
Home-page: https://github.com/Jsakkos/mkv-episode-matcher
Author: Jonathan Sakkos
Author-email: Jsakkos <jonathansakkos@gmail.com>
License: MIT License
Project-URL: Documentation, https://github.com/Jsakkos/mkv-episode-matcher#readme
Project-URL: Issues, https://github.com/Jsakkos/mkv-episode-matcher/issues
Project-URL: Source, https://github.com/Jsakkos/mkv-episode-matcher
Classifier: Development Status :: 4 - Beta
Classifier: Programming Language :: Python
Classifier: Programming Language :: Python :: 3.12
Classifier: Programming Language :: Python :: Implementation :: CPython
Classifier: Programming Language :: Python :: Implementation :: PyPy
Requires-Python: <3.15,>=3.10
License-File: LICENSE
Requires-Dist: chardet>=5.2.0
Requires-Dist: configparser>=7.1.0
Requires-Dist: ffmpeg>=1.4
Requires-Dist: librosa>=0.10.2
Requires-Dist: loguru>=0.7.2
Requires-Dist: nemo-toolkit[asr]>=2.0.0
Requires-Dist: opensubtitlescom>=0.1.5
Requires-Dist: rapidfuzz>=3.10.1
Requires-Dist: requests>=2.32.3
Requires-Dist: rich[jupyter]>=13.9.4
Requires-Dist: soundfile>=0.12.1
Requires-Dist: tmdb-client>=0.0.1
Requires-Dist: torch>=2.0.0
Requires-Dist: torchaudio>=2.0.0
Requires-Dist: torchvision>=0.15.0
Requires-Dist: typer>=0.9.0
Requires-Dist: customtkinter>=5.2.2
Requires-Dist: packaging>=23.0
Requires-Dist: pydantic>=2.0.0
Requires-Dist: pydantic-settings>=2.0.0
Requires-Dist: ty>=0.0.7
Requires-Dist: fastapi>=0.110.0
Requires-Dist: uvicorn[standard]>=0.29.0
Requires-Dist: python-multipart>=0.0.9
Provides-Extra: cu128
Requires-Dist: torch>=2.9.1; sys_platform != "darwin" and extra == "cu128"
Requires-Dist: torchvision>=0.24.1; sys_platform != "darwin" and extra == "cu128"
Provides-Extra: nemo
Requires-Dist: nemo_toolkit[asr]>=2.0.0; extra == "nemo"
Dynamic: license-file
